kaikeba_flow/__init__.py
kaikeba_flow/nn/__init__.py
kaikeba_flow/nn/core.py
kaikeba_flow/utils/__init__.py
kaikeba_flow/utils/utilities.py
kaikeba_flow-0.0.1.dist-info/LICENSE
kaikeba_flow-0.0.1.dist-info/METADATA
kaikeba_flow-0.0.1.dist-info/WHEEL
kaikeba_flow-0.0.1.dist-info/top_level.txt
kaikeba_flow-0.0.1.dist-info/RECORD
