Metadata-Version: 2.1
Name: kaikeba-flow
Version: 0.0.1
Summary: This is a mini but function completed neural networks framework
Home-page: UNKNOWN
Author: Minchiuan Gao
Author-email: minchiuan@zju.edu.cn
License: UNKNOWN
Platform: UNKNOWN
Classifier: Programming Language :: Python :: 3
Classifier: License :: OSI Approved :: MIT License
Classifier: Operating System :: OS Independent
Requires-Python: >=3.6
